CHANGES.rst
MANIFEST.in
README.md
setup.py
src/WeChatPay/WeChatPay.py
src/WeChatPay/__init__.py
src/WeChatPay.egg-info/PKG-INFO
src/WeChatPay.egg-info/SOURCES.txt
src/WeChatPay.egg-info/dependency_links.txt
src/WeChatPay.egg-info/not-zip-safe
src/WeChatPay.egg-info/top_level.txt
src/wechatpay.egg-info/SOURCES.txt