Metadata-Version: 1.1
Name: wechatpay
Version: 1.0.8
Summary: Python-Django WeChat payment API.
Home-page: https://github.com/hereischen/WeChat
Author: Haotong Chen
Author-email: hereischen@gmail.com
License: BSD License
Platform: UNKNOWN
Classifier: Development Status :: 5 - Production/Stable
Classifier: Intended Audience :: Developers
Classifier: Topic :: Software Development :: Build Tools
Classifier: License :: OSI Approved :: BSD License
Classifier: Programming Language :: Python :: 2.7
